_grgl.cpython-38-x86_64-linux-gnu.so
gconverter
gindexer
grg-merge
grgl
grgp
pygrgl/__init__.py
pygrgl/cli.py
pygrgl/display.py
pygrgl/grg.py
pygrgl/clicmd/__init__.py
pygrgl/clicmd/common.py
pygrgl/clicmd/construct.py
pygrgl/clicmd/convert.py
pygrgl/clicmd/merge.py
pygrgl/clicmd/process.py
pygrgl/clicmd/split.py
pygrgl-2.3.dist-info/LICENSE
pygrgl-2.3.dist-info/METADATA
pygrgl-2.3.dist-info/WHEEL
pygrgl-2.3.dist-info/entry_points.txt
pygrgl-2.3.dist-info/top_level.txt
pygrgl-2.3.dist-info/RECORD
