Metadata-Version: 2.1
Name: pygrgl
Version: 2.3
Summary: Genotype Representation Graph Library
Home-page: https://aprilweilab.github.io/
Author: Drew DeHaas, April Wei
Author-email: 
Classifier: Programming Language :: Python :: 3
Classifier: Operating System :: MacOS
Classifier: Operating System :: POSIX :: Linux
License-File: LICENSE
Requires-Dist: tqdm
